<?xml version="1.0" encoding="utf-8" ?>
<dwsync>
<file name="update.php" server="startau.spd.co.il:55" local="129637826980682008" remote="129663698400000000" />
<file name="manage.php" server="startau.spd.co.il:55" local="129637827549724555" remote="129663698400000000" />
<file name="create.php" server="startau.spd.co.il:55" local="129637827844841435" remote="129663698400000000" />
<file name="_search.php" server="startau.spd.co.il:55" local="129636147332422096" remote="129663698400000000" />
<file name="_form.php" server="startau.spd.co.il:55" local="129636147743185590" remote="129663698400000000" />
<file name="update.php" server="startau.spd.co.il:55//sites/miss.org.il/" local="129637826980682008" remote="129757631400000000" />
<file name="manage.php" server="startau.spd.co.il:55//sites/miss.org.il/" local="129637827549724555" remote="129757631400000000" />
<file name="create.php" server="startau.spd.co.il:55//sites/miss.org.il/" local="129637827844841435" remote="129757631400000000" />
<file name="_search.php" server="startau.spd.co.il:55//sites/miss.org.il/" local="129636147332422096" remote="129757631400000000" />
<file name="_form.php" server="startau.spd.co.il:55//sites/miss.org.il/" local="129636147743185590" remote="129757631400000000" />
<file name="create.php" server="startau.spd.co.il:55//sites/taunet.co.il/new/" local="129761213480856911" remote="129761217000000000" />
<file name="manage.php" server="startau.spd.co.il:55//sites/taunet.co.il/new/" local="129761213225012277" remote="129761217000000000" />
<file name="update.php" server="startau.spd.co.il:55//sites/taunet.co.il/new/" local="129761212419196187" remote="129761217000000000" />
<file name="_form.php" server="startau.spd.co.il:55//sites/taunet.co.il/new/" local="129761214688135963" remote="129761217000000000" />
<file name="_search.php" server="startau.spd.co.il:55//sites/taunet.co.il/new/" local="129761213937083006" remote="129761217000000000" />
</dwsync>